{"appid":350740,"name":"The Bug Butcher","tags":["Indie","Action","Shoot 'Em Up","Arcade","Local Co-Op","Co-op","Singleplayer","Bullet Hell","Great Soundtrack","Difficult","Sci-fi","Fast-Paced","Cartoony","2D","Multiplayer","Early Access","Platformer"],"flags":[2,39,22,28,29,23,15,25,43,44,1,38,9],"specs":{"storage":1},"parentappid":"","cooptimus":{"url":"https://www.co-optimus.com/game/4059/PC/the-bug-butcher.html","local":"2","online":"0","lan":"0","splitscreen":"0","dropindropout":"0","campaign":"0","featurelist":["Co-Op Modes"]}}