{"appid":481870,"name":"Mini Thief","tags":["Strategy","Indie","Casual","Stealth","Multiplayer","Crime","Pixel Graphics","Co-op","Sandbox","Funny","Difficult","Family Friendly","Simulation","Atmospheric","Replay Value","Great Soundtrack","Roguelite","Walking Simulator","Comedy","Early Access"],"flags":[2,36,39,22,28,29,44,1,38,9],"specs":{"storage":0.01},"parentappid":"","cooptimus":{"url":"https://www.co-optimus.com/game/8432/PC/mini-thief.html","local":"2","online":"0","lan":"0","splitscreen":"0","dropindropout":"0","campaign":"0","featurelist":["Co-Op Modes"]}}