{"appid":1281400,"name":"Good Knight","parentappid":"","flags":[2,39,22,28,23,15,25,44,1,38,9],"tags":["Early Access","Puzzle","Bullet Hell","Difficult","Indie","Gothic","Arcade","Shooter","Top-Down","Bullet Time","Co-op","Local Co-Op","Casual","Action","Multiplayer","Singleplayer","Local Multiplayer","Shoot 'Em Up","Cinematic","Twin Stick Shooter"],"cooptimus":{"url":"https://www.co-optimus.com/game/8038/PC/good-knight.html","local":"2","online":"2","lan":"0","splitscreen":"0","dropindropout":"0","campaign":"1","featurelist":["Campaign Co-Op"]}}