{"appid":446760,"name":"Neighborhorde","tags":["Local Co-Op","Party Game","Local Multiplayer","4 Player Local","Party","Co-op","Family Friendly","Cute","Indie","Shoot 'Em Up","Roguelite","Twin Stick Shooter","Hack and Slash","Zombies","Survival","GameMaker","Arcade","Action","Difficult","Singleplayer"],"flags":[2,39,22,28,29,43,44,38,9],"specs":{"storage":0.05},"parentappid":"","cooptimus":{"url":"https://www.co-optimus.com/game/4042/PC/neighborhorde.html","local":"4","online":"0","lan":"0","splitscreen":"0","dropindropout":"1","campaign":"1","featurelist":["Drop-In/Drop-Out","Campaign Co-Op"]}}