{"appid":351970,"name":"Tales of Zestiria","parentappid":"","flags":[2,22,28,29,23,41,42,43,44,1,38,9],"tags":["JRPG","Anime","RPG","Fantasy","Story Rich","Open World","Action RPG","Adventure","Great Soundtrack","Singleplayer","Action","Co-op","Multiplayer","Action-Adventure","Local Co-Op","Atmospheric","Cute","Hack and Slash","Third Person","Female Protagonist"],"cooptimus":{"url":"https://www.co-optimus.com/game/3996/PC/tales-of-zestiria.html","local":"4","online":"0","lan":"0","splitscreen":"0","dropindropout":"1","campaign":"1","featurelist":["Drop-In/Drop-Out","Campaign Co-Op"]}}