{"appid":221040,"name":"Resident Evil 6","tags":["Action","Zombies","Co-op","Third-Person Shooter","Horror","Adventure","Co-op Campaign","Online Co-Op","Multiplayer","Third Person","Shooter","Quick-Time Events","Split Screen","Local Co-Op","Survival","Survival Horror","Singleplayer","Atmospheric","Female Protagonist","Casual"],"flags":[2,22,29,18,23,8,25,44,1,38,9],"specs":false,"parentappid":"","cooptimus":{"url":"https://www.co-optimus.com/game/2466/PC/resident-evil-6.html","local":"2","online":"2","lan":"0","splitscreen":"1","dropindropout":"0","campaign":"1","featurelist":["Splitscreen","Campaign Co-Op"]}}