{"appid":1011670,"name":"Totally Reliable Delivery Service","tags":["Action","Casual","Sandbox","Physics","Funny","Co-op","Open World","Simulation","3D","Action-Adventure","Local Multiplayer","Third Person","Adventure","Split Screen","Cute","Colorful","Comedy","4 Player Local","Local Co-Op","Multiplayer"],"flags":[2,38,39,22,28,44,1,9],"specs":{"storage":4},"parentappid":"","cooptimus":{"url":"https://www.co-optimus.com/game/6258/PC/totally-reliable-delivery-service.html","local":"4","online":"4","lan":"0","splitscreen":"1","dropindropout":"1","campaign":"1","featurelist":["Splitscreen","Drop-In/Drop-Out","Campaign Co-Op"]}}