{"appid":404590,"name":"Vikings - Wolves of Midgard","tags":["RPG","Hack and Slash","Action","Action RPG","Mythology","Fantasy","Isometric","Co-op","Multiplayer","Vikings","Gore","Singleplayer","Online Co-Op","Medieval","Loot","Local Co-Op","Violent","Nudity","Adventure","Dark Fantasy"],"flags":[2,38,22,28,29,23,44,1,9],"specs":{"storage":10},"parentappid":"","cooptimus":{"url":"https://www.co-optimus.com/game/4282/PC/vikings-wolves-of-midgard.html","local":"2","online":"2","lan":"0","splitscreen":"0","dropindropout":"0","campaign":"1","featurelist":["Campaign Co-Op"]}}