{"appid":628670,"name":"Hellpoint","tags":["Souls-like","Action","Sci-fi","RPG","Multiplayer","Indie","Adventure","Co-op","Action RPG","Atmospheric","Dark","Hack and Slash","Horror","Lovecraftian","Third Person","Singleplayer","Split Screen","Psychological Horror","Co-op Campaign","Difficult"],"flags":[2,36,38,39,22,28,29,43,44,1,9],"specs":{"storage":6},"parentappid":"","cooptimus":{"url":"https://www.co-optimus.com/game/6320/PC/hellpoint.html","local":"2","online":"2","lan":"0","splitscreen":"1","dropindropout":"1","campaign":"1","featurelist":["Splitscreen","Drop-In/Drop-Out","Campaign Co-Op"]}}