{"appid":527230,"name":"For The King","tags":["Open World","Strategy","RPG","Online Co-Op","Roguelike","Adventure","Multiplayer","Turn-Based","Co-op","Tabletop","Roguelite","Turn-Based Combat","Turn-Based Strategy","Party-Based RPG","Indie","Board Game","Fantasy","Strategy RPG","Hex Grid","Local Co-Op"],"flags":[2,36,37,38,39,22,28,29,23,41,42,43,44,1,9],"specs":{"storage":3},"parentappid":"","cooptimus":{"url":"https://www.co-optimus.com/game/5085/PC/for-the-king.html","local":"3","online":"3","lan":"0","splitscreen":"0","dropindropout":"0","campaign":"1","featurelist":["Campaign Co-Op"]}}