{"appid":1029210,"name":"30XX","tags":["Early Access","Action","Indie","Platformer","2D Platformer","Co-op","Roguelite","Roguelike","Pixel Graphics","Local Co-Op","Side Scroller","Procedural Generation","Local Multiplayer","Action Roguelike","Online Co-Op","Controller","Female Protagonist","Adventure","2D","Colorful"],"flags":[2,38,39,28,23,17,43,44,9],"specs":{"storage":2},"parentappid":"","cooptimus":{"url":"https://www.co-optimus.com/game/6193/PC/30xx.html","local":"2","online":"2","lan":"0","splitscreen":"0","dropindropout":"0","campaign":"1","featurelist":["Campaign Co-Op"]}}