{"appid":313690,"name":"LEGO® Batman™ 3: Beyond Gotham","tags":["LEGO","Adventure","Action","Superhero","Open World","Multiplayer","Local Co-Op","Funny","Space","Comedy","Co-op","Family Friendly","Third Person","Singleplayer","Puzzle","Controller","Comic Book","Sandbox","Split Screen","Online Co-Op"],"flags":[2,22,28,23,41,42,43,44,1,38,9],"specs":{"storage":10},"parentappid":"","cooptimus":{"url":"https://www.co-optimus.com/game/3435/PC/lego-batman-3-beyond-gotham.html","local":"2","online":"0","lan":"0","splitscreen":"1","dropindropout":"0","campaign":"1","featurelist":["Splitscreen","Campaign Co-Op"]}}