{"appid":887170,"name":"Vortex Of Pain","tags":["Early Access","Beat 'em up","Fighting","Arcade","Side Scroller","Local Multiplayer","Retro","1980s","Spectacle fighter","Local Co-Op","Funny","Co-op","3D Fighter","Physics","4 Player Local","Singleplayer","Sci-fi","Action","Wrestling","3D"],"flags":[2,37,39,28,44,38,9],"specs":{"storage":3},"parentappid":"","cooptimus":{"url":"https://www.co-optimus.com/game/5727/PC/vortex-of-pain.html","local":"4","online":"0","lan":"0","splitscreen":"0","dropindropout":"0","campaign":"1","featurelist":["Campaign Co-Op"]}}