{"appid":1200770,"name":"Deathground","parentappid":"","flags":[2,38,48,22,28,23],"tags":["Horror","Survival Horror","PvE","Hunting","Stealth","Hacking","Dinosaurs","Survival","Action-Adventure","First-Person","3D","Psychological Horror","Action","Team-Based","Thriller","Atmospheric","Crafting","Adventure","Physics","Dark"],"cooptimus":{"url":"https://www.co-optimus.com/game/7534/PC/deathground.html","local":"0","online":"3","lan":"3","splitscreen":"0","dropindropout":"0","campaign":"0","featurelist":["Co-Op Modes"]}}