{"appid":402710,"name":"Osiris: New Dawn","parentappid":"","flags":[2,36,38,1,9],"tags":["Open World Survival Craft","Horror","Survival","Space","Open World","Multiplayer","Sci-fi","Building","Adventure","Crafting","Sandbox","Early Access","Base Building","Co-op","Action","Singleplayer","RPG","Aliens","Indie","FPS"],"cooptimus":{"url":"https://www.co-optimus.com/game/4351/PC/osiris-new-dawn.html","local":"0","online":"12","lan":"0","splitscreen":"0","dropindropout":"0","campaign":"1","featurelist":["Campaign Co-Op"]}}