{"appid":1604030,"name":"V Rising","tags":["Survival","Crafting","PvE","PvP","Open World","Vampire","Building","Base Building","Hack and Slash","Sandbox","Massively Multiplayer","Action-Adventure","Action","Adventure","Exploration","Multiplayer","Online Co-Op","Dark Fantasy","Medieval","Combat"],"flags":[2,36,38,1,49,9,20],"specs":{"storage":4},"parentappid":"","cooptimus":{"url":"https://www.co-optimus.com/game/10582/PC/v-rising.html","local":"0","online":"10","lan":"0","splitscreen":"0","dropindropout":"1","campaign":"0","featurelist":["Drop-In/Drop-Out","Co-Op Modes"]}}