{"appid":308600,"name":"Geneshift","tags":["Early Access","Action","Indie","RPG","Battle Royale","Top-Down Shooter","Multiplayer","Shooter","Top-Down","Co-op Campaign","Casual","Online Co-Op","Tactical","2D","Strategy","Co-op","Massively Multiplayer"],"flags":[2,36,38,22,28,29,17,1,9,20],"specs":{"storage":0.512},"parentappid":"","cooptimus":{"url":"https://www.co-optimus.com/game/4624/PC/geneshift.html","local":"0","online":"4","lan":"0","splitscreen":"0","dropindropout":"0","campaign":"1","featurelist":["Campaign Co-Op"]}}